pytest_claude_agent_sdk/__init__.py
pytest_claude_agent_sdk/fixtures.py
pytest_claude_agent_sdk/plugin.py
pytest_claude_agent_sdk/spy.py
pytest_claude_agent_sdk-0.1.1.dist-info/METADATA
pytest_claude_agent_sdk-0.1.1.dist-info/WHEEL
pytest_claude_agent_sdk-0.1.1.dist-info/entry_points.txt
pytest_claude_agent_sdk-0.1.1.dist-info/licenses/LICENSE
pytest_claude_agent_sdk-0.1.1.dist-info/RECORD
