Metadata-Version: 2.4
Name: pytest-claude-agent-sdk
Version: 0.1.1
Summary: Use Claude Code in your pytests, or pytest your own Claude Code agents — or both
Project-URL: Homepage, https://github.com/amyodov/pytest-claude-agent-sdk
Project-URL: Repository, https://github.com/amyodov/pytest-claude-agent-sdk
Project-URL: Issues, https://github.com/amyodov/pytest-claude-agent-sdk/issues
Author-email: Alexander Myodov <amyodov@gmail.com>
License-Expression: MIT
License-File: LICENSE
Classifier: Development Status :: 3 - Alpha
Classifier: Framework :: Pytest
Classifier: Intended Audience :: Developers
Classifier: License :: OSI Approved :: MIT License
Classifier: Programming Language :: Python :: 3
Classifier: Programming Language :: Python :: 3.10
Classifier: Programming Language :: Python :: 3.11
Classifier: Programming Language :: Python :: 3.12
Classifier: Programming Language :: Python :: 3.13
Classifier: Topic :: Software Development :: Testing
Requires-Python: >=3.10
Requires-Dist: claude-agent-sdk
Requires-Dist: pytest-asyncio>=0.21.0
Requires-Dist: pytest>=6.0
Provides-Extra: dev
Requires-Dist: mypy; extra == 'dev'
Requires-Dist: ruff; extra == 'dev'
Requires-Dist: uv-publish; extra == 'dev'
